{"status":"done","publicPath":"static/js/","chunks":{"frontend":[{"name":"index.js","publicPath":"static/js/index.js","path":"C:\\Users\\rober\\Google Drive\\Programming\\al-turn-labelling\\frontend\\static\\js\\index.js"}]},"error":"ModuleBuildError","message":"Module build failed (from ./node_modules/babel-loader/lib/index.js):\nSyntaxError: C:\\Users\\rober\\Google Drive\\Programming\\al-turn-labelling\\frontend\\src\\components\\coding_classes\\DeleteModal.js: Unexpected token, expected \"}\" (31:50)\n\n  29 |       <Modal.Footer>\n  30 |         <ButtonGroup>\n> 31 |           <Button onClick={() => {handleDelete()} >Delete</Button>\n     |                                                   ^\n  32 |           <Button>Cancel</Button>\n  33 |         </ButtonGroup>\n  34 |       </Modal.Footer>\n    at Object._raise (C:\\Users\\rober\\Google Drive\\Programming\\al-turn-labelling\\node_modules\\@babel\\parser\\lib\\index.js:766:17)\n    at Object.raiseWithData (C:\\Users\\rober\\Google Drive\\Programming\\al-turn-labelling\\node_modules\\@babel\\parser\\lib\\index.js:759:17)\n    at Object.raise (C:\\Users\\rober\\Google Drive\\Programming\\al-turn-labelling\\node_modules\\@babel\\parser\\lib\\index.js:753:17)\n    at Object.unexpected (C:\\Users\\rober\\Google Drive\\Programming\\al-turn-labelling\\node_modules\\@babel\\parser\\lib\\index.js:8966:16)\n    at Object.expect (C:\\Users\\rober\\Google Drive\\Programming\\al-turn-labelling\\node_modules\\@babel\\parser\\lib\\index.js:8952:28)\n    at Object.jsxParseExpressionContainer (C:\\Users\\rober\\Google Drive\\Programming\\al-turn-labelling\\node_modules\\@babel\\parser\\lib\\index.js:4572:10)\n    at Object.jsxParseAttributeValue (C:\\Users\\rober\\Google Drive\\Programming\\al-turn-labelling\\node_modules\\@babel\\parser\\lib\\index.js:4536:21)\n    at Object.jsxParseAttribute (C:\\Users\\rober\\Google Drive\\Programming\\al-turn-labelling\\node_modules\\@babel\\parser\\lib\\index.js:4587:44)\n    at Object.jsxParseOpeningElementAfterName (C:\\Users\\rober\\Google Drive\\Programming\\al-turn-labelling\\node_modules\\@babel\\parser\\lib\\index.js:4607:28)\n    at Object.jsxParseOpeningElementAt (C:\\Users\\rober\\Google Drive\\Programming\\al-turn-labelling\\node_modules\\@babel\\parser\\lib\\index.js:4600:17)"}